fullscope_mcp_server/__init__.py
fullscope_mcp_server/server.py
iflow_mcp_yzfly_fullscope_mcp_server-1.0.1.dist-info/licenses/LICENSE
iflow_mcp_yzfly_fullscope_mcp_server-1.0.1.dist-info/METADATA
iflow_mcp_yzfly_fullscope_mcp_server-1.0.1.dist-info/WHEEL
iflow_mcp_yzfly_fullscope_mcp_server-1.0.1.dist-info/entry_points.txt
iflow_mcp_yzfly_fullscope_mcp_server-1.0.1.dist-info/top_level.txt
iflow_mcp_yzfly_fullscope_mcp_server-1.0.1.dist-info/RECORD
