Metadata-Version: 2.4
Name: iflow-mcp_yzfly_fullscope-mcp-server
Version: 1.0.1
Summary: FullScope-MCP: 内容总结运营 MCP Server，支持网页抓取、文件读取、内容总结、主题汇总等功能
Author-email: yzfly <yz.liu.me@gmail.com>
License: Apache-2.0
Project-URL: Homepage, https://github.com/yzfly/fullscope-mcp
Project-URL: Repository, https://github.com/yzfly/fullscope-mcp
Project-URL: Documentation, https://github.com/yzfly/fullscope-mcp#readme
Project-URL: Bug Tracker, https://github.com/yzfly/fullscope-mcp/issues
Project-URL: Author's Blog, https://www.npmjs.com/~langgpt
Keywords: mcp,content,summarization,web-scraping,ai
Classifier: Development Status :: 4 - Beta
Classifier: Intended Audience :: Developers
Classifier: License :: OSI Approved :: Apache Software License
Classifier: Programming Language :: Python :: 3
Classifier: Programming Language :: Python :: 3.10
Classifier: Programming Language :: Python :: 3.11
Classifier: Programming Language :: Python :: 3.12
Classifier: Topic :: Software Development :: Libraries :: Python Modules
Classifier: Topic :: Text Processing :: General
Classifier: Topic :: Internet :: WWW/HTTP :: Indexing/Search
Requires-Python: >=3.10
License-File: LICENSE
Requires-Dist: mcp>=1.2.0
Requires-Dist: httpx>=0.25.0
Requires-Dist: beautifulsoup4>=4.12.0
Requires-Dist: PyPDF2>=3.0.0
Requires-Dist: openai>=1.0.0
Requires-Dist: requests>=2.31.0
Provides-Extra: dev
Requires-Dist: pytest>=7.0.0; extra == "dev"
Requires-Dist: pytest-asyncio>=0.21.0; extra == "dev"
Requires-Dist: black>=23.0.0; extra == "dev"
Requires-Dist: isort>=5.12.0; extra == "dev"
Requires-Dist: mypy>=1.0.0; extra == "dev"
Dynamic: license-file
